xcoll/__init__.py
xcoll/beam_elements/__init__.py
xcoll/beam_elements/absorber.py
xcoll/beam_elements/base.py
xcoll/beam_elements/blowup.py
xcoll/beam_elements/elements_src/black_absorber.h
xcoll/beam_elements/elements_src/black_crystal.h
xcoll/beam_elements/elements_src/blowup.h
xcoll/beam_elements/elements_src/emittance_monitor.h
xcoll/beam_elements/elements_src/everest_block.h
xcoll/beam_elements/elements_src/everest_collimator.h
xcoll/beam_elements/elements_src/everest_crystal.h
xcoll/beam_elements/elements_src/fluka_collimator.h
xcoll/beam_elements/elements_src/fluka_crystal.h
xcoll/beam_elements/elements_src/geant4_collimator.h
xcoll/beam_elements/elements_src/geant4_collimator_tip.h
xcoll/beam_elements/elements_src/rf_sweep.h
xcoll/beam_elements/elements_src/transparent_collimator.h
xcoll/beam_elements/elements_src/transparent_crystal.h
xcoll/beam_elements/everest.py
xcoll/beam_elements/fluka.py
xcoll/beam_elements/geant4.py
xcoll/beam_elements/monitor.py
xcoll/beam_elements/sweep.py
xcoll/beam_elements/transparent.py
xcoll/colldb.py
xcoll/compare.py
xcoll/constants/__init__.py
xcoll/constants/aggregate_constants.py
xcoll/general.py
xcoll/geometry.md
xcoll/headers/checks.h
xcoll/headers/particle_states.py
xcoll/initial_distribution.py
xcoll/interaction_record/__init__.py
xcoll/interaction_record/interaction_record.py
xcoll/interaction_record/interaction_record_src/interaction_record.h
xcoll/interaction_record/interaction_types.py
xcoll/json.py
xcoll/line_tools.py
xcoll/lossmap.py
xcoll/materials/__init__.py
xcoll/materials/allotropes.py
xcoll/materials/atoms.py
xcoll/materials/compounds.py
xcoll/materials/database.py
xcoll/materials/material.py
xcoll/materials/mixtures.py
xcoll/materials/parameters.py
xcoll/materials/sixtrack.py
xcoll/particles_tree.py
xcoll/plot.py
xcoll/prebuilt_kernel_definitions/__init__.py
xcoll/prebuilt_kernel_definitions/element_inits.py
xcoll/prebuilt_kernel_definitions/element_types.py
xcoll/pretty_print.py
xcoll/rf_sweep.py
xcoll-0.9.4.dist-info/METADATA
xcoll-0.9.4.dist-info/WHEEL
xcoll-0.9.4.dist-info/entry_points.txt
xcoll-0.9.4.dist-info/licenses/LICENSE
xcoll-0.9.4.dist-info/licenses/NOTICE
xcoll-0.9.4.dist-info/RECORD
