Metadata-Version: 2.4
Name: xcoll
Version: 0.9.4
Summary: Xsuite collimation package
License: Apache-2.0
License-File: LICENSE
License-File: NOTICE
Author: Frederik F. Van der Veken
Author-email: frederik@cern.ch
Requires-Python: >=3.10
Classifier: License :: OSI Approved :: Apache Software License
Classifier: Programming Language :: Python :: 3
Classifier: Programming Language :: Python :: 3.10
Classifier: Programming Language :: Python :: 3.11
Classifier: Programming Language :: Python :: 3.12
Classifier: Programming Language :: Python :: 3.13
Classifier: Programming Language :: Python :: 3.14
Provides-Extra: tests
Requires-Dist: meson
Requires-Dist: numpy (>=1.0)
Requires-Dist: pandas (>=1.4)
Requires-Dist: pytest ; extra == "tests"
Requires-Dist: pytest-html ; extra == "tests"
Requires-Dist: pytest-xdist ; extra == "tests"
Requires-Dist: ruamel-yaml (>=0.17.31,<0.18.15)
Requires-Dist: xdeps (>=0.10.10)
Requires-Dist: xobjects (>=0.5.12)
Requires-Dist: xpart (>=0.23.7)
Requires-Dist: xtrack (>=0.98.12)
Project-URL: Bug Tracker, https://github.com/xsuite/xsuite/issues
Project-URL: Documentation, https://xsuite.readthedocs.io/
Project-URL: Homepage, https://github.com/xsuite/xcoll
Project-URL: Repository, https://github.com/xsuite/xcoll
Project-URL: download, https://pypi.python.org/pypi/xcoll
